spacy_loggers/__init__.py
spacy_loggers/util.py
spacy_loggers/wandb.py
spacy_loggers/tests/__init__.py
spacy_loggers/tests/test_registry.py
spacy_loggers-1.0.2.dist-info/LICENSE
spacy_loggers-1.0.2.dist-info/METADATA
spacy_loggers-1.0.2.dist-info/WHEEL
spacy_loggers-1.0.2.dist-info/entry_points.txt
spacy_loggers-1.0.2.dist-info/top_level.txt
spacy_loggers-1.0.2.dist-info/zip-safe
spacy_loggers-1.0.2.dist-info/RECORD
