Metadata-Version: 2.1
Name: spacy-loggers
Version: 1.0.2
Summary: Logging utilities for SpaCy
Home-page: https://github.com/explosion/spacy-loggers
Author: Explosion
Author-email: contact@explosion.ai
License: MIT
Platform: UNKNOWN
Requires-Python: >=3.6
License-File: LICENSE
